pytun.py
setup.py
pytun.egg-info/PKG-INFO
pytun.egg-info/SOURCES.txt
pytun.egg-info/dependency_links.txt
pytun.egg-info/top_level.txt